Metadata-Version: 1.1
Name: behave2cucumber-py3
Version: 1.0.4
Summary: Behave to Cucumber json converter
Home-page: https://github.com/asc3ns10n/behave2cucumber
Author: Andrey Goldgamer, Zvika Messing
Author-email: andrey.goldgamer@behalf.com, zvika@behalf.com 
License: MIT
Keywords: behave2cucumber setuptools development cucumber behave automation json
Platform: UNKNOWN
Classifier: Development Status :: 5 - Production/Stable
Classifier: Intended Audience :: Developers
Classifier: Topic :: Software Development :: Testing
Classifier: License :: OSI Approved :: MIT License
Classifier: Programming Language :: Python :: 3
